Mux8to1/mux8to1.v
`timescale 1ns / 1ps
//////////////////////////////////////////////////////////////////////////////////
// Company: 
// Engineer: 
// 
// Create Date: 2024/04/23 14:39:36
// Design Name: 
// Module Name: mux8to1
// Project Name: 
// Target Devices: 
// Tool Versions: 
// Description: 
// 
// Dependencies: 
// 
// Revision:
// Revision 0.01 - File Created
// Additional Comments:
// 
//////////////////////////////////////////////////////////////////////////////////


module mux8to1(
    input i0,
    input i1,
    input i2,
    input i3,
    input i4,
    input i5,
    input i6,
    input i7,
    input s0,
    input s1,
    input s2,
    output reg o
    );
    always @ (i0 or i1 or i2 or i3 or i4 or i5 or i6 or i7 or s0 or s1 or s2)
    begin
    case ({s2, s1, s0}) // 使用花括号组合选择信号
        3'b000: o = i0; // 当选择信号为 3'b000 时，选择输入 i0
        3'b001: o = i1; // 当选择信号为 3'b001 时，选择输入 i1
        3'b010: o = i2; // 当选择信号为 3'b010 时，选择输入 i2
        3'b011: o = i3; // 当选择信号为 3'b011 时，选择输入 i3
        3'b100: o = i4; // 当选择信号为 3'b100 时，选择输入 i4
        3'b101: o = i5; // 当选择信号为 3'b101 时，选择输入 i5
        3'b110: o = i6; // 当选择信号为 3'b110 时，选择输入 i6
        3'b111: o = i7; // 当选择信号为 3'b111 时，选择输入 i7
        default: o = 1'b0; // 如果选择信号不在上述范围内，默认输出0
    endcase
    end
endmodule

Mux8to1/simux8to1.v
`timescale 1ns / 1ps
//////////////////////////////////////////////////////////////////////////////////
// Company: 
// Engineer: 
// 
// Create Date: 2024/04/23 14:39:36
// Design Name: 
// Module Name: simux8to1
// Project Name: 
// Target Devices: 
// Tool Versions: 
// Description: 
// 
// Dependencies: 
// 
// Revision:
// Revision 0.01 - File Created
// Additional Comments:
// 
//////////////////////////////////////////////////////////////////////////////////

// mux8to1_tb.v
`timescale 1ns/1ns

module mux8to1_tb;

    // Parameters
    parameter CLK_PERIOD = 10; // Clock period in ns

    // Inputs
    reg i0, i1, i2, i3, i4, i5, i6, i7;
    reg s0, s1, s2;
    reg clk;

    // Outputs
    wire o;

    // Instantiate the mux8to1 module
    mux8to1 uut (
        .i0(i0),
        .i1(i1),
        .i2(i2),
        .i3(i3),
        .i4(i4),
        .i5(i5),
        .i6(i6),
        .i7(i7),
        .s0(s0),
        .s1(s1),
        .s2(s2),
        .o(o)
    );

    // Clock generation
    always #((CLK_PERIOD)/2) clk = ~clk;

    // Test stimulus
    initial begin
        $dumpfile("wave.vcd");        //生成的vcd文件名称
        $dumpvars(0, mux8to1_tb);    //tb模块名称
        // Initialize inputs
        i0 = 1'b1; i1 = 1'b0; i2 = 1'b1; i3 = 1'b0;
        i4 = 1'b1; i5 = 1'b0; i6 = 1'b1; i7 = 1'b0;
        s0 = 1'b0; s1 = 1'b0; s2 = 1'b0;

        // Apply stimulus
        #100 s0 = 1'b1; s1 = 1'b0; s2 = 1'b0; // Select input i0
        #100 s0 = 1'b0; s1 = 1'b1; s2 = 1'b0; // Select input i1
        #100 s0 = 1'b1; s1 = 1'b1; s2 = 1'b0; // Select input i2
        #100 s0 = 1'b0; s1 = 1'b0; s2 = 1'b1; // Select input i3
        #100 s0 = 1'b1; s1 = 1'b0; s2 = 1'b1; // Select input i4
        #100 s0 = 1'b0; s1 = 1'b1; s2 = 1'b1; // Select input i5
        #100 s0 = 1'b1; s1 = 1'b1; s2 = 1'b1; // Select input i6
        #100 s0 = 1'b0; s1 = 1'b0; s2 = 1'b0; // Select input i7

        // Add more test cases as needed

        // End simulation
       #10 $finish;
    end

endmodule

Mux8to1/wave.vcd
$date
	Tue Apr 30 15:19:50 2024
$end
$version
	Icarus Verilog
$end
$timescale
	1ps
$end
$scope module mux8to1_tb $end
$var wire 1 ! o $end
$var parameter 32 " CLK_PERIOD $end
$var reg 1 # clk $end
$var reg 1 $ i0 $end
$var reg 1 % i1 $end
$var reg 1 & i2 $end
$var reg 1 ' i3 $end
$var reg 1 ( i4 $end
$var reg 1 ) i5 $end
$var reg 1 * i6 $end
$var reg 1 + i7 $end
$var reg 1 , s0 $end
$var reg 1 - s1 $end
$var reg 1 . s2 $end
$scope module uut $end
$var wire 1 $ i0 $end
$var wire 1 % i1 $end
$var wire 1 & i2 $end
$var wire 1 ' i3 $end
$var wire 1 ( i4 $end
$var wire 1 ) i5 $end
$var wire 1 * i6 $end
$var wire 1 + i7 $end
$var wire 1 , s0 $end
$var wire 1 - s1 $end
$var wire 1 . s2 $end
$var reg 1 ! o $end
$upscope $end
$upscope $end
$enddefinitions $end
$comment Show the parameter values. $end
$dumpall
b1010 "
$end
#0
$dumpvars
0.
0-
0,
0+
1*
0)
1(
0'
1&
0%
1$
x#
1!
$end
#100000
0!
1,
#200000
1!
1-
0,
#300000
0!
1,
#400000
1!
1.
0-
0,
#500000
0!
1,
#600000
1!
1-
0,
#700000
0!
1,
#800000
1!
0.
0-
0,
